ssmbak/__init__.py
ssmbak/backup/Dockerfile
ssmbak/backup/__init__.py
ssmbak/backup/ssmbak.py
ssmbak/cli/__init__.py
ssmbak/cli/backup_all.py
ssmbak/cli/cfn.py
ssmbak/cli/cli.py
ssmbak/cli/helpers.py
ssmbak/cli/stack.py
ssmbak/data/cfn.yml
ssmbak/py.typed
ssmbak/restore/__init__.py
ssmbak/restore/actions.py
ssmbak/restore/aws.py
ssmbak/typing.py
ssmbak-0.3.2.dist-info/METADATA
ssmbak-0.3.2.dist-info/WHEEL
ssmbak-0.3.2.dist-info/entry_points.txt
ssmbak-0.3.2.dist-info/licenses/LICENSE
ssmbak-0.3.2.dist-info/RECORD
