Metadata-Version: 2.4
Name: ssmbak
Version: 0.3.2
Summary: Event-driven SSM Param backups and point-in-time restore.
License: MIT
License-File: LICENSE
Author: olmouse
Author-email: olmouse@newvoll.net
Requires-Python: >=3.10,<4.0
Classifier: License :: OSI Approved :: MIT License
Classifier: Programming Language :: Python :: 3
Classifier: Programming Language :: Python :: 3.10
Classifier: Programming Language :: Python :: 3.11
Classifier: Programming Language :: Python :: 3.12
Classifier: Programming Language :: Python :: 3.13
Classifier: Programming Language :: Python :: 3.14
Requires-Dist: boto3 (>=1.26.39,<2.0.0)
Requires-Dist: cfn-lint (>=1.40.4,<2.0.0)
Requires-Dist: prettytable (>=3.5.0,<4.0.0)
Requires-Dist: typing-extensions (>=4.0,<5.0) ; python_version < "3.11"
Project-URL: Documentation, https://ssmbak.readthedocs.io/en/latest/index.html
Project-URL: Homepage, https://github.com/newvoll/ssmbak
Project-URL: Issues, https://github.com/newvoll/ssmbak/issues
Project-URL: Repository, https://github.com/newvoll/ssmbak
